formog2p/__init__.py
formog2p/py.typed
formog2p/data/english/lexicon_cmu.json
formog2p/data/english/lexicon_sinica.json
formog2p/data/hakka/lexicon/ipa/客語_南四縣.json
formog2p/data/hakka/lexicon/ipa/客語_四縣.json
formog2p/data/hakka/lexicon/ipa/客語_大埔.json
formog2p/data/hakka/lexicon/ipa/客語_海陸.json
formog2p/data/hakka/lexicon/ipa/客語_詔安.json
formog2p/data/hakka/lexicon/ipa/客語_饒平.json
formog2p/data/hakka/lexicon/pinyin/客語_南四縣.json
formog2p/data/hakka/lexicon/pinyin/客語_四縣.json
formog2p/data/hakka/lexicon/pinyin/客語_大埔.json
formog2p/data/hakka/lexicon/pinyin/客語_海陸.json
formog2p/data/hakka/lexicon/pinyin/客語_詔安.json
formog2p/data/hakka/lexicon/pinyin/客語_饒平.json
formog2p/data/hakka/share/variant_map.json
formog2p/hakka/__init__.py
formog2p/hakka/g2p.py
formog2p/hakka/word_segment.py
formog2p-0.1.1.dist-info/METADATA
formog2p-0.1.1.dist-info/WHEEL
formog2p-0.1.1.dist-info/licenses/LICENSE
formog2p-0.1.1.dist-info/RECORD
