Metadata-Version: 2.4
Name: formog2p
Version: 0.1.1
Summary: Formosan Languages Grapheme-to-Phoneme (G2P) Toolkit - 台灣本土語言文字轉音素工具
Project-URL: Homepage, https://github.com/hungshinlee/formospeech-g2p
Project-URL: Repository, https://github.com/hungshinlee/formospeech-g2p
Project-URL: Issues, https://github.com/hungshinlee/formospeech-g2p/issues
Project-URL: Changelog, https://github.com/hungshinlee/formospeech-g2p/blob/main/CHANGELOG.md
Author: HS
License-Expression: MIT
License-File: LICENSE
Keywords: g2p,hakka,nlp,taiwanese,tokenization,台灣,客語
Classifier: Development Status :: 4 - Beta
Classifier: License :: OSI Approved :: MIT License
Classifier: Natural Language :: Chinese (Traditional)
Classifier: Operating System :: OS Independent
Classifier: Programming Language :: Python :: 3
Classifier: Programming Language :: Python :: 3.10
Classifier: Programming Language :: Python :: 3.11
Classifier: Programming Language :: Python :: 3.12
Classifier: Programming Language :: Python :: 3.13
Classifier: Topic :: Text Processing :: Linguistic
Requires-Python: >=3.10
Requires-Dist: jieba>=0.42.1
Provides-Extra: dev
Requires-Dist: pre-commit>=4.0.0; extra == 'dev'
Requires-Dist: pytest>=8.0.0; extra == 'dev'
Requires-Dist: ruff>=0.4.0; extra == 'dev'
